{
    "data":[
        {
"brandID": -1,
"brandName": "",
"categoryID": -1,
"categoryName": "",
"defaultPrice": 150,
"dealerPrice": 100,
"sku":"ADX100",
"inventory": 54,
"inventoryCost":200,
"lowStockAlertQuantity": "",
"price": 50,
"productID": 3,
"productName": "product in kg",
"soldIn": 2,
"unitName": "Kilogram",
"variantID": 9,
"variantName": ""
        },
        {
"brandID": -1,
"brandName": "",
"categoryID": -1,
"categoryName": "",
"defaultPrice": 180,
"dealerPrice": 130,
"sku":"ADX100",
"inventory": 54,
"inventoryCost":200,
"lowStockAlertQuantity": "",
"price": 150,
"productID": 6,
"productName": "Aloo Chat",
"soldIn": 2,
"unitName": "Kilogram",
"variantID": 9,
"variantName": ""
        },
        {
"brandID": -1,
"brandName": "",
"categoryID": -1,
"categoryName": "",
"defaultPrice": 150,
"dealerPrice": 80,
"sku":"ADX100",
"inventory": 54,
"inventoryCost":200,
"lowStockAlertQuantity": "",
"price": 150,
"productID": 78,
"productName": "Chakki Atta",
"soldIn": 2,
"unitName": "Kilogram",
"variantID": 9,
"variantName": ""
        },
        {
"brandID": -1,
"brandName": "",
"categoryID": -1,
"categoryName": "",
"defaultPrice": 150,
"dealerPrice": 50,
"sku":"ADX100",
"inventory": 54,
"inventoryCost":200,
"lowStockAlertQuantity": "",
"price": 150,
"productID": 9,
"productName": "Basmati Rice",
"soldIn": 2,
"unitName": "Kilogram",
"variantID": 9,
"variantName": ""
        }      
    ]
}
